adgs/Syndbox.py
adgs/__init__.py
"adgs-0.0.1.dist-info/LICENSE,txt"
adgs-0.0.1.dist-info/METADATA
adgs-0.0.1.dist-info/WHEEL
adgs-0.0.1.dist-info/top_level.txt
adgs-0.0.1.dist-info/RECORD
