Metadata-Version: 2.1
Name: adgs
Version: 0.0.1
Summary: artificial-data-generation space
Author-email: Radhwane Derraz <derrazradhwane@gmail.com>
Project-URL: Homepage, https://doi.org/10.1016/j.compag.2023.107646
Project-URL: Bug Tracker, https://doi.org/10.1016/j.compag.2023.107646
Classifier: Programming Language :: Python :: 3
Classifier: License :: OSI Approved :: Apache Software License
Classifier: Operating System :: OS Independent
Requires-Python: >=3.7
License-File: LICENSE,txt
